liblistloader/__init__.py
liblistloader/desiquintans_nounlist.py
liblistloader-1.0.1.post2.dist-info/LICENSE
liblistloader-1.0.1.post2.dist-info/METADATA
liblistloader-1.0.1.post2.dist-info/WHEEL
liblistloader-1.0.1.post2.dist-info/top_level.txt
liblistloader-1.0.1.post2.dist-info/RECORD
