Metadata-Version: 2.1
Name: liblistloader
Version: 1.0.1.post2
Summary: Library for loading of word lists
Home-page: https://git.bbaovanc.com/bbaovanc/liblistloader
Author: BBaoVanC
Author-email: pypi@bbaovanc.com
License: UNKNOWN
Platform: UNKNOWN
Classifier: Programming Language :: Python :: 3
Classifier: License :: OSI Approved :: GNU General Public License v3 (GPLv3)
Classifier: Operating System :: OS Independent
Requires-Python: >=3.7
License-File: LICENSE
